[{"data":{"id":"DotNetCore-Pack","source":null,"target":null}},{"data":{"id":"0581a7f9-864a-4912-b8fb-986e343da8ab","source":"DotNetCore-Pack","target":"DotNetCore-Build"}},{"data":{"id":"DotNetCore-Build","source":null,"target":null}},{"data":{"id":"53e208d8-adf7-4411-a2f5-12274d0c4bf3","source":"DotNetCore-Build","target":"Clean"}},{"data":{"id":"107b844e-5f11-48f5-8bf7-e33573c0b110","source":"DotNetCore-Build","target":"DotNetCore-Restore"}},{"data":{"id":"DotNetCore-Restore","source":null,"target":null}},{"data":{"id":"Clean","source":null,"target":null}},{"data":{"id":"ff5252cb-ae78-4766-808f-6c018e1c9205","source":"Clean","target":"Show-Info"}},{"data":{"id":"a1a1873a-c75c-4ef4-87de-afadf653338a","source":"Clean","target":"Print-AppVeyor-Environment-Variables"}},{"data":{"id":"Print-AppVeyor-Environment-Variables","source":null,"target":null}},{"data":{"id":"Show-Info","source":null,"target":null}}]